pythonGPT/__init__.py
pythonGPT/pythonGPT.py
pythonGPT3-1.0.1.dist-info/LICENSE.txt
pythonGPT3-1.0.1.dist-info/METADATA
pythonGPT3-1.0.1.dist-info/WHEEL
pythonGPT3-1.0.1.dist-info/top_level.txt
pythonGPT3-1.0.1.dist-info/RECORD
