Metadata-Version: 2.1
Name: pythonGPT3
Version: 1.0.1
Summary: "The ChatGPT Requests module is a Python package that provides a convenient interface for making requests to the ChatGPT language model."
Home-page: https://gitlab.com/codasteroid/basicpkg
Author: Ahmed Sheded
Author-email: sheded222@gmail.com
Project-URL: Bug Tracker, https://github.com/AhmedSheded/pythonGPT/issues
Project-URL: repository, https://gitlab.com/AhmedSheded/pythonGPT
Classifier: Programming Language :: Python :: 3
Classifier: License :: OSI Approved :: MIT License
Classifier: Operating System :: OS Independent
Requires-Python: >=3.6
License-File: LICENSE.txt
